{"product_name":"Jotapipe AC 1010, Jotun Czech A.S.","epd_id":"NEPD-2685-1385-EN","compliance":["EN 15804","ISO 14025","ISO 21930"],"producer_name":"Jotun A/S","environmental_impact":[{"parameter":"GWP-total","unit":"kg CO2-eq.","values":[{"value":"7,07E+00","module":"A1-A3"}]},{"parameter":"ODP","unit":"kg CFC 11-eq.","values":[{"value":"1,44E-07","module":"A1-A3"}]},{"parameter":"AP","unit":"kg SO2-eq.","values":[{"value":"2,53E-02","module":"A1-A3"}]},{"parameter":"EP","unit":"kg Phosphat-eq.","values":[{"value":"7,18E-03","module":"A1-A3"}]},{"parameter":"POCP","unit":"kg Ethen-eq.","values":[{"value":"2,00E-03","module":"A1-A3"}]},{"parameter":"ADPE","unit":"kg Sb-eq.","values":[{"value":"1,48E-04","module":"A1-A3"}]},{"parameter":"ADPF","unit":"MJ","values":[{"value":"9,89E+01","module":"A1-A3"}]},{"parameter":"ADPM","unit":"kg Sb-eq.","values":[{"value":"1,48E-04","module":"A1-A3"}]}],"additional_environmental_impact":[],"resource_use":[{"parameter":"PERE","unit":"MJ","values":[{"value":"3,57E+00","module":"A1-A3"}]},{"parameter":"PERM","unit":"MJ","values":[{"value":"1,28E+00","module":"A1-A3"}]},{"parameter":"PERT","unit":"MJ","values":[{"value":"4,85E+00","module":"A1-A3"}]},{"parameter":"PENRE","unit":"MJ","values":[{"value":"1,09E+02","module":"A1-A3"}]},{"parameter":"PENRM","unit":"MJ","values":[{"value":"0,0E+00","module":"A1-A3"}]},{"parameter":"PENRT","unit":"MJ","values":[{"value":"1,09E+02","module":"A1-A3"}]},{"parameter":"SM","unit":"kg","values":[{"value":"0,0E+00","module":"A1-A3"}]},{"parameter":"RSF","unit":"MJ","values":[{"value":"0,0E+00","module":"A1-A3"}]},{"parameter":"NRSF","unit":"MJ","values":[{"value":"0,0E+00","module":"A1-A3"}]},{"parameter":"FW","unit":"m3","values":[{"value":"4,34E-01","module":"A1-A3"}]}],"end_of_life_waste":[{"parameter":"HWD","unit":"kg","values":[{"value":"1,88E-04","module":"A1-A3"}]},{"parameter":"NHWD","unit":"kg","values":[{"value":"9,47E-01","module":"A1-A3"}]},{"parameter":"RWD","unit":"kg","values":[{"value":"0,0E+00","module":"A1-A3"}]}],"end_of_life_flow":[{"parameter":"CRU","unit":"kg","values":[{"value":"0,0E+00","module":"A1-A3"}]},{"parameter":"MFR","unit":"kg","values":[{"value":"2,59E-03","module":"A1-A3"}]},{"parameter":"MER","unit":"kg","values":[{"value":"6,48E-03","module":"A1-A3"}]},{"parameter":"EEE","unit":"MJ","values":[{"value":"0,0E+00","module":"A1-A3"}]},{"parameter":"EET","unit":"MJ","values":[{"value":"0,0E+00","module":"A1-A3"}]}]}